pymzml/__init__.py
pymzml/decoder.py
pymzml/file_interface.py
pymzml/ms_numpress.py
pymzml/obo.py
pymzml/plot.py
pymzml/plot_revised.py
pymzml/regex_patterns.py
pymzml/run.py
pymzml/spec.py
pymzml/version.txt
pymzml/file_classes/__init__.py
pymzml/file_classes/bytesMzml.py
pymzml/file_classes/indexedGzip.py
pymzml/file_classes/standardGzip.py
pymzml/file_classes/standardMzml.py
pymzml/obo/psi-ms-1.0.0.obo.gz
pymzml/obo/psi-ms-1.1.0.obo.gz
pymzml/obo/psi-ms-1.10.0.obo.gz
pymzml/obo/psi-ms-1.11.0.obo.gz
pymzml/obo/psi-ms-1.12.0.obo.gz
pymzml/obo/psi-ms-1.12.1.obo.gz
pymzml/obo/psi-ms-1.12.2.obo.gz
pymzml/obo/psi-ms-1.13.0.obo.gz
pymzml/obo/psi-ms-1.13.1.obo.gz
pymzml/obo/psi-ms-1.13.2.obo.gz
pymzml/obo/psi-ms-1.14.0.obo.gz
pymzml/obo/psi-ms-1.15.0.obo.gz
pymzml/obo/psi-ms-1.16.0.obo.gz
pymzml/obo/psi-ms-1.17.0.obo.gz
pymzml/obo/psi-ms-1.17.1.obo.gz
pymzml/obo/psi-ms-1.18.0.obo.gz
pymzml/obo/psi-ms-1.18.1.obo.gz
pymzml/obo/psi-ms-1.18.2.obo.gz
pymzml/obo/psi-ms-1.2.0.obo.gz
pymzml/obo/psi-ms-1.2.1.obo.gz
pymzml/obo/psi-ms-1.3.0.obo.gz
pymzml/obo/psi-ms-1.3.1.obo.gz
pymzml/obo/psi-ms-1.4.0.obo.gz
pymzml/obo/psi-ms-1.5.0.obo.gz
pymzml/obo/psi-ms-1.6.0.obo.gz
pymzml/obo/psi-ms-1.7.0.obo.gz
pymzml/obo/psi-ms-1.8.0.obo.gz
pymzml/obo/psi-ms-1.8.1.obo.gz
pymzml/obo/psi-ms-1.9.0.obo.gz
pymzml/obo/psi-ms-1.9.1.obo.gz
pymzml/obo/psi-ms-1.9.2.obo.gz
pymzml/obo/psi-ms-2.0.0.obo.gz
pymzml/obo/psi-ms-2.01.0.obo.gz
pymzml/obo/psi-ms-2.1.0.obo.gz
pymzml/obo/psi-ms-2.13.0.obo.gz
pymzml/obo/psi-ms-2.14.0.obo.gz
pymzml/obo/psi-ms-2.14.1.obo.gz
pymzml/obo/psi-ms-2.14.2.obo.gz
pymzml/obo/psi-ms-2.14.3.obo.gz
pymzml/obo/psi-ms-2.14.4.obo.gz
pymzml/obo/psi-ms-2.15.0.obo.gz
pymzml/obo/psi-ms-2.16.0.obo.gz
pymzml/obo/psi-ms-2.17.0.obo.gz
pymzml/obo/psi-ms-2.17.1.obo.gz
pymzml/obo/psi-ms-2.18.0.obo.gz
pymzml/obo/psi-ms-2.19.0.obo.gz
pymzml/obo/psi-ms-2.2.0.obo.gz
pymzml/obo/psi-ms-2.2.1.obo.gz
pymzml/obo/psi-ms-2.20.0.obo.gz
pymzml/obo/psi-ms-2.20.1.obo.gz
pymzml/obo/psi-ms-2.20.2.obo.gz
pymzml-2.5.11.dist-info/AUTHORS.txt
pymzml-2.5.11.dist-info/LICENSE.txt
pymzml-2.5.11.dist-info/METADATA
pymzml-2.5.11.dist-info/WHEEL
pymzml-2.5.11.dist-info/top_level.txt
pymzml-2.5.11.dist-info/RECORD
